Metadata-Version: 1.0
Name: pyguishudi
Version: 1.0.1
Summary: find the operator by phone
Home-page: https://github.com/MrLawes/pyguishudi
Author: Lawes
Author-email: haiou_chen@sina.cn
License: MIT
Platform: UNKNOWN
